{"stdlib":{"lib":{"node_modules":{"@stdlib":{"array":{"buffer":true,"complex128":true,"complex64":true,"convert-same":true,"convert":true,"ctors":true,"dtype":true,"dtypes":true,"float32":true,"float64":true,"from-iterator":true,"int16":true,"int32":true,"int8":true,"min-dtype":true,"next-dtype":true,"__namespace__":true,"pool":true,"promotion-rules":true,"reviver":true,"safe-casts":true,"same-kind-casts":true,"shape":true,"shared-buffer":true,"to-circular-iterator":true,"to-iterator-right":true,"to-iterator":true,"to-json":true,"to-sparse-iterator-right":true,"to-sparse-iterator":true,"to-strided-iterator":true,"to-view-iterator-right":true,"to-view-iterator":true,"typed-complex-ctors":true,"typed-complex-dtypes":true,"typed-ctors":true,"typed-dtypes":true,"typed":true,"uint16":true,"uint32":true,"uint8":true,"uint8c":true},"assert":{"contains":true,"deep-equal":true,"deep-has-own-property":true,"deep-has-property":true,"has-arraybuffer-support":true,"has-async-await-support":true,"has-async-iterator-symbol-support":true,"has-class-support":true,"has-define-properties-support":true,"has-define-property-support":true,"has-float32array-support":true,"has-float64array-support":true,"has-function-name-support":true,"has-generator-support":true,"has-globalthis-support":true,"has-int16array-support":true,"has-int32array-support":true,"has-int8array-support":true,"has-iterator-symbol-support":true,"has-map-support":true,"has-node-buffer-support":true,"has-own-property":true,"has-property":true,"has-proxy-support":true,"has-set-support":true,"has-sharedarraybuffer-support":true,"has-symbol-support":true,"has-tostringtag-support":true,"has-uint16array-support":true,"has-uint32array-support":true,"has-uint8array-support":true,"has-uint8clampedarray-support":true,"has-wasm-support":true,"has-weakmap-support":true,"has-weakset-support":true,"instance-of":true,"is-absolute-path":true,"is-accessor-property-in":true,"is-accessor-property":true,"is-alphagram":true,"is-alphanumeric":true,"is-anagram":true,"is-arguments":true,"is-array-array":true,"is-array-length":true,"is-array-like-object":true,"is-array-like":true,"is-array":true,"is-arraybuffer":true,"is-ascii":true,"is-between-array":true,"is-between":true,"is-big-endian":true,"is-binary-string":true,"is-boolean-array":true,"is-boolean":true,"is-boxed-primitive":true,"is-browser":true,"is-buffer":true,"is-capitalized":true,"is-centrosymmetric-matrix":true,"is-circular-array":true,"is-circular-plain-object":true,"is-circular":true,"is-collection":true,"is-complex-like":true,"is-complex-typed-array":true,"is-complex":true,"is-complex128":true,"is-complex128array":true,"is-complex64":true,"is-complex64array":true,"is-configurable-property-in":true,"is-configurable-property":true,"is-darwin":true,"is-data-property-in":true,"is-data-property":true,"is-date-object-array":true,"is-date-object":true,"is-digit-string":true,"is-electron-main":true,"is-electron-renderer":true,"is-electron":true,"is-email-address":true,"is-empty-array":true,"is-empty-object":true,"is-empty-string":true,"is-enumerable-property-in":true,"is-enumerable-property":true,"is-error":true,"is-eval-error":true,"is-even":true,"is-falsy-array":true,"is-falsy":true,"is-finite-array":true,"is-finite":true,"is-float32array":true,"is-float64array":true,"is-function-array":true,"is-function":true,"is-generator-object-like":true,"is-generator-object":true,"is-hex-string":true,"is-infinite":true,"is-inherited-property":true,"is-int16array":true,"is-int32array":true,"is-int8array":true,"is-integer-array":true,"is-integer":true,"is-iterable-like":true,"is-iterator-like":true,"is-json":true,"is-leap-year":true,"is-little-endian":true,"is-lowercase":true,"is-matrix-like":true,"is-method-in":true,"is-method":true,"is-named-typed-tuple-like":true,"is-nan-array":true,"is-nan":true,"is-native-function":true,"is-ndarray-like":true,"is-negative-integer-array":true,"is-negative-integer":true,"is-negative-number-array":true,"is-negative-number":true,"is-negative-zero":true,"is-node-builtin":true,"is-node-duplex-stream-like":true,"is-node-readable-stream-like":true,"is-node-repl":true,"is-node-stream-like":true,"is-node-transform-stream-like":true,"is-node-writable-stream-like":true,"is-node":true,"is-nonconfigurable-property-in":true,"is-nonconfigurable-property":true,"is-nonenumerable-property-in":true,"is-nonenumerable-property":true,"is-nonnegative-integer-array":true,"is-nonnegative-integer":true,"is-nonnegative-number-array":true,"is-nonnegative-number":true,"is-nonpositive-integer-array":true,"is-nonpositive-integer":true,"is-nonpositive-number-array":true,"is-nonpositive-number":true,"is-nonsymmetric-matrix":true,"is-null-array":true,"is-null":true,"is-number-array":true,"is-number":true,"is-numeric-array":true,"is-object-array":true,"is-object-like":true,"is-object":true,"is-odd":true,"is-persymmetric-matrix":true,"is-plain-object-array":true,"is-plain-object":true,"is-positive-integer-array":true,"is-positive-integer":true,"is-positive-number-array":true,"is-positive-number":true,"is-positive-zero":true,"is-primitive-array":true,"is-primitive":true,"is-prng-like":true,"is-probability-array":true,"is-probability":true,"is-prototype-of":true,"is-range-error":true,"is-read-only-property-in":true,"is-read-only-property":true,"is-read-write-property-in":true,"is-read-write-property":true,"is-readable-property-in":true,"is-readable-property":true,"is-reference-error":true,"is-regexp-string":true,"is-regexp":true,"is-relative-path":true,"is-safe-integer-array":true,"is-safe-integer":true,"is-same-value-zero":true,"is-same-value":true,"is-sharedarraybuffer":true,"is-skew-centrosymmetric-matrix":true,"is-skew-persymmetric-matrix":true,"is-skew-symmetric-matrix":true,"is-square-matrix":true,"is-strict-equal":true,"is-string-array":true,"is-string":true,"is-symbol-array":true,"is-symbol":true,"is-symmetric-matrix":true,"is-syntax-error":true,"is-truthy-array":true,"is-truthy":true,"is-type-error":true,"is-typed-array-length":true,"is-typed-array-like":true,"is-typed-array":true,"is-uint16array":true,"is-uint32array":true,"is-uint8array":true,"is-uint8clampedarray":true,"is-unc-path":true,"is-undefined-or-null":true,"is-undefined":true,"is-unity-probability-array":true,"is-uppercase":true,"is-uri-error":true,"is-uri":true,"is-vector-like":true,"is-web-worker":true,"is-whitespace":true,"is-windows":true,"is-writable-property-in":true,"is-writable-property":true,"is-write-only-property-in":true,"is-write-only-property":true,"__namespace__":true,"tools":{"array-function":true,"array-like-function":true,"__namespace__":true,"typed-array-function":true}},"bench":{"harness":true,"__namespace__":true},"blas":{"base":{"dasum":true,"daxpy":true,"dcopy":true,"ddot":true,"gasum":true,"gaxpy":true,"gcopy":true,"__namespace__":true,"sasum":true,"saxpy":true,"scopy":true,"sdot":true,"sscal":true},"__namespace__":true},"buffer":{"alloc-unsafe":true,"ctor":true,"from-array":true,"from-arraybuffer":true,"from-buffer":true,"from-string":true,"__namespace__":true,"reviver":true,"to-json":true},"complex":{"cmplx":true,"conj":true,"float32":true,"float64":true,"imag":true,"__namespace__":true,"real":true,"reim":true,"reviver-float32":true,"reviver-float64":true,"reviver":true},"constants":{"array":{"max-array-length":true,"max-typed-array-length":true,"__namespace__":true},"math":{"complex128-num-bytes":true,"complex64-num-bytes":true,"float16-cbrt-eps":true,"float16-eps":true,"float16-exponent-bias":true,"float16-max-safe-integer":true,"float16-max":true,"float16-min-safe-integer":true,"float16-ninf":true,"float16-num-bytes":true,"float16-pinf":true,"float16-precision":true,"float16-smallest-normal":true,"float16-smallest-subnormal":true,"float16-sqrt-eps":true,"float32-cbrt-eps":true,"float32-eps":true,"float32-exponent-bias":true,"float32-max-safe-integer":true,"float32-max":true,"float32-min-safe-integer":true,"float32-ninf":true,"float32-num-bytes":true,"float32-pinf":true,"float32-precision":true,"float32-smallest-normal":true,"float32-smallest-subnormal":true,"float32-sqrt-eps":true,"float64-apery":true,"float64-catalan":true,"float64-cbrt-eps":true,"float64-e":true,"float64-eps":true,"float64-eulergamma":true,"float64-exponent-bias":true,"float64-fourth-pi":true,"float64-fourth-root-eps":true,"float64-gamma-lanczos-g":true,"float64-glaisher-kinkelin":true,"float64-half-ln-two":true,"float64-half-pi":true,"float64-high-word-exponent-mask":true,"float64-high-word-significand-mask":true,"float64-ln-half":true,"float64-ln-pi":true,"float64-ln-sqrt-two-pi":true,"float64-ln-ten":true,"float64-ln-two-pi":true,"float64-ln-two":true,"float64-log10-e":true,"float64-log2-e":true,"float64-max-base10-exponent-subnormal":true,"float64-max-base10-exponent":true,"float64-max-base2-exponent-subnormal":true,"float64-max-base2-exponent":true,"float64-max-ln":true,"float64-max-safe-fibonacci":true,"float64-max-safe-integer":true,"float64-max-safe-lucas":true,"float64-max-safe-nth-fibonacci":true,"float64-max-safe-nth-lucas":true,"float64-max":true,"float64-min-base10-exponent-subnormal":true,"float64-min-base10-exponent":true,"float64-min-base2-exponent-subnormal":true,"float64-min-base2-exponent":true,"float64-min-ln":true,"float64-min-safe-integer":true,"float64-ninf":true,"float64-num-bytes":true,"float64-phi":true,"float64-pi-squared":true,"float64-pi":true,"float64-pinf":true,"float64-precision":true,"float64-smallest-normal":true,"float64-smallest-subnormal":true,"float64-sqrt-eps":true,"float64-sqrt-half-pi":true,"float64-sqrt-half":true,"float64-sqrt-phi":true,"float64-sqrt-pi":true,"float64-sqrt-three":true,"float64-sqrt-two-pi":true,"float64-sqrt-two":true,"float64-two-pi":true,"int16-max":true,"int16-min":true,"int16-num-bytes":true,"int32-max":true,"int32-min":true,"int32-num-bytes":true,"int8-max":true,"int8-min":true,"int8-num-bytes":true,"__namespace__":true,"uint16-max":true,"uint16-num-bytes":true,"uint32-max":true,"uint32-num-bytes":true,"uint8-max":true,"uint8-num-bytes":true},"__namespace__":true,"string":{"__namespace__":true,"path-delimiter-posix":true,"path-delimiter-win32":true,"path-delimiter":true,"path-sep-posix":true,"path-sep-win32":true,"path-sep":true,"unicode-max-bmp":true,"unicode-max":true},"time":{"hours-in-day":true,"hours-in-week":true,"milliseconds-in-day":true,"milliseconds-in-hour":true,"milliseconds-in-minute":true,"milliseconds-in-second":true,"milliseconds-in-week":true,"minutes-in-day":true,"minutes-in-hour":true,"minutes-in-week":true,"months-in-year":true,"__namespace__":true,"seconds-in-day":true,"seconds-in-hour":true,"seconds-in-minute":true,"seconds-in-week":true}},"crypto":{"arc4":true,"__namespace__":true},"datasets":{"afinn-111":true,"afinn-96":true,"anscombes-quartet":true,"berndt-cps-wages-1985":true,"cdc-nchs-us-births-1969-1988":true,"cdc-nchs-us-births-1994-2003":true,"cdc-nchs-us-infant-mortality-bw-1915-2013":true,"cmudict":true,"dale-chall-new":true,"emoji-code-picto":true,"emoji-picto-code":true,"emoji":true,"female-first-names-en":true,"fivethirtyeight-ffq":true,"frb-sf-wage-rigidity":true,"harrison-boston-house-prices-corrected":true,"harrison-boston-house-prices":true,"herndon-venus-semidiameters":true,"img-acanthus-mollis":true,"img-airplane-from-above":true,"img-allium-oreophilum":true,"img-black-canyon":true,"img-dust-bowl-home":true,"img-french-alpine-landscape":true,"img-locomotion-house-cat":true,"img-locomotion-nude-male":true,"img-march-pastoral":true,"img-nagasaki-boats":true,"liu-negative-opinion-words-en":true,"liu-positive-opinion-words-en":true,"male-first-names-en":true,"minard-napoleons-march":true,"moby-dick":true,"month-names-en":true,"nightingales-rose":true,"pace-boston-house-prices":true,"__namespace__":true,"savoy-stopwords-fin":true,"savoy-stopwords-fr":true,"savoy-stopwords-ger":true,"savoy-stopwords-it":true,"savoy-stopwords-por":true,"savoy-stopwords-sp":true,"savoy-stopwords-swe":true,"sotu":true,"spache-revised":true,"spam-assassin":true,"ssa-us-births-2000-2014":true,"standard-card-deck":true,"stopwords-en":true,"suthaharan-multi-hop-sensor-network":true,"suthaharan-single-hop-sensor-network":true,"us-states-abbr":true,"us-states-capitals-names":true,"us-states-capitals":true,"us-states-names-capitals":true,"us-states-names":true},"error":{"__namespace__":true,"reviver":true,"to-json":true},"fastmath":{"__namespace__":true,"special":{"abs":true,"acosh":true,"alpha-max-plus-beta-min":true,"asinh":true,"atanh":true,"hypot":true,"max":true,"min":true,"__namespace__":true,"pow-int":true,"uint32-log2":true,"uint32-sqrt":true}},"fs":{"close":true,"exists":true,"open":true,"__namespace__":true,"read-dir":true,"read-file-list":true,"read-file":true,"read-json":true,"read-wasm":true,"rename":true,"resolve-parent-path":true,"unlink":true,"write-file":true},"iter":{"advance":true,"any-by":true,"any":true,"concat":true,"constant":true,"counter":true,"datespace":true,"dedupe-by":true,"dedupe":true,"empty":true,"every-by":true,"every":true,"fill":true,"filter-map":true,"filter":true,"first":true,"flow":true,"for-each":true,"head":true,"incrspace":true,"intersection-by-hash":true,"intersection":true,"last":true,"length":true,"linspace":true,"logspace":true,"map":true,"mapn":true,"none-by":true,"none":true,"nth":true,"__namespace__":true,"pipeline-thunk":true,"pipeline":true,"pop":true,"push":true,"reject":true,"replicate-by":true,"replicate":true,"shift":true,"slice":true,"some-by":true,"some":true,"step":true,"strided-by":true,"strided":true,"to-array-view-right":true,"to-array-view":true,"union":true,"unique-by-hash":true,"unique-by":true,"unique":true,"unitspace":true,"unshift":true},"math":{"base":{"assert":{"int32-is-even":true,"int32-is-odd":true,"is-even":true,"is-finite":true,"is-infinite":true,"is-integer":true,"is-nan":true,"is-negative-integer":true,"is-negative-zero":true,"is-nonnegative-integer":true,"is-nonpositive-integer":true,"is-odd":true,"is-positive-integer":true,"is-positive-zero":true,"is-probability":true,"is-safe-integer":true,"__namespace__":true,"uint32-is-pow2":true},"complex":{"abs":true,"abs2":true,"add":true,"ceil":true,"ceiln":true,"cis":true,"divide":true,"exp":true,"flipsign":true,"floor":true,"floorn":true,"inv":true,"multiply":true,"negate":true,"__namespace__":true,"phase":true,"polar":true,"round":true,"roundn":true,"signum":true,"subtract":true},"__namespace__":true,"special":{"abs":true,"abs2":true,"acos":true,"acosh":true,"acoth":true,"acovercos":true,"acoversin":true,"ahavercos":true,"ahaversin":true,"asin":true,"asinh":true,"atan":true,"atan2":true,"atanh":true,"avercos":true,"aversin":true,"bernoulli":true,"besselj0":true,"besselj1":true,"bessely0":true,"bessely1":true,"beta":true,"betainc":true,"betaincinv":true,"betaln":true,"binet":true,"binomcoef":true,"binomcoefln":true,"boxcox":true,"boxcox1p":true,"boxcox1pinv":true,"boxcoxinv":true,"cbrt":true,"ceil":true,"ceil10":true,"ceil2":true,"ceilb":true,"ceiln":true,"ceilsd":true,"clamp":true,"copysign":true,"cos":true,"cosh":true,"cosm1":true,"cospi":true,"covercos":true,"coversin":true,"deg2rad":true,"digamma":true,"dirac-delta":true,"dirichlet-eta":true,"ellipe":true,"ellipk":true,"erf":true,"erfc":true,"erfcinv":true,"erfinv":true,"exp":true,"exp10":true,"exp2":true,"expit":true,"expm1":true,"expm1rel":true,"factorial":true,"factorialln":true,"falling-factorial":true,"fibonacci-index":true,"fibonacci":true,"flipsign":true,"floor":true,"floor10":true,"floor2":true,"floorb":true,"floorn":true,"floorsd":true,"fresnel":true,"fresnelc":true,"fresnels":true,"frexp":true,"gamma-delta-ratio":true,"gamma-lanczos-sum-expg-scaled":true,"gamma-lanczos-sum":true,"gamma":true,"gamma1pm1":true,"gammainc":true,"gammaincinv":true,"gammaln":true,"gcd":true,"hacovercos":true,"hacoversin":true,"havercos":true,"haversin":true,"heaviside":true,"hypot":true,"imul":true,"imuldw":true,"int32-abs":true,"inv":true,"kernel-betainc":true,"kernel-betaincinv":true,"kernel-cos":true,"kernel-sin":true,"kernel-tan":true,"kronecker-delta":true,"lcm":true,"ldexp":true,"ln":true,"log":true,"log10":true,"log1mexp":true,"log1p":true,"log1pexp":true,"log2":true,"logaddexp":true,"logit":true,"lucas":true,"max":true,"maxabs":true,"min":true,"minabs":true,"minmax":true,"minmaxabs":true,"modf":true,"negafibonacci":true,"negalucas":true,"nonfibonacci":true,"__namespace__":true,"pdiff":true,"polygamma":true,"pow":true,"powm1":true,"rad2deg":true,"ramp":true,"rempio2":true,"riemann-zeta":true,"rising-factorial":true,"round":true,"round10":true,"round2":true,"roundb":true,"roundn":true,"roundsd":true,"rsqrt":true,"sici":true,"signum":true,"sin":true,"sinc":true,"sincos":true,"sincospi":true,"sinh":true,"sinpi":true,"spence":true,"sqrt":true,"sqrt1pm1":true,"tan":true,"tanh":true,"trigamma":true,"trunc":true,"trunc10":true,"trunc2":true,"truncb":true,"truncn":true,"truncsd":true,"uimul":true,"uimuldw":true,"vercos":true,"versin":true,"wrap":true,"xlog1py":true,"xlogy":true},"tools":{"continued-fraction":true,"evalpoly-compile":true,"evalpoly":true,"evalrational-compile":true,"evalrational":true,"fibpoly":true,"hermitepoly":true,"lucaspoly":true,"normhermitepoly":true,"__namespace__":true,"sum-series":true},"utils":{"absolute-difference":true,"float64-epsilon-difference":true,"__namespace__":true,"relative-difference":true}},"iter":{"add":true,"divide":true,"fibonacci":true,"mod":true,"multiply":true,"nonfibonacci":true,"__namespace__":true,"subtract":true},"__namespace__":true,"utils":{"incrspace":true,"linspace":true,"logspace":true,"__namespace__":true}},"ml":{"incr":{"kmeans":true},"online-binary-classification":true,"online-sgd-regression":true,"__namespace__":true},"namespace":{"alias2pkg":true,"alias2related":true,"aliases":true,"__namespace__":true,"pkg2alias":true,"pkg2related":true},"ndarray":{"array":true,"base":{"assert":{"is-allowed-data-type-cast":true,"is-buffer-length-compatible-shape":true,"is-buffer-length-compatible":true,"is-casting-mode":true,"is-column-major-contiguous":true,"is-column-major":true,"is-contiguous":true,"is-data-type":true,"is-index-mode":true,"is-order":true,"is-row-major-contiguous":true,"is-row-major":true,"is-safe-data-type-cast":true,"is-same-kind-data-type-cast":true,"is-single-segment-compatible":true,"__namespace__":true},"bind2vind":true,"buffer-ctors":true,"buffer-dtype":true,"buffer":true,"bytes-per-element":true,"clamp-index":true,"ctor":true,"dtype-char":true,"ind":true,"ind2sub":true,"iteration-order":true,"max-view-buffer-index":true,"memoized-ctor":true,"min-view-buffer-index":true,"minmax-view-buffer-index":true,"numel":true,"__namespace__":true,"shape2strides":true,"strides2offset":true,"strides2order":true,"sub2ind":true,"to-array":true,"vind2bind":true,"wrap-index":true},"casting-modes":true,"ctor":true,"dtypes":true,"ind2sub":true,"index-modes":true,"memoized-ctor":true,"min-dtype":true,"next-dtype":true,"orders":true,"__namespace__":true,"promotion-rules":true,"safe-casts":true,"same-kind-casts":true,"sub2ind":true},"net":{"http-server":true,"__namespace__":true},"nlp":{"expand-contractions":true,"lda":true,"__namespace__":true,"porter-stemmer":true,"tokenize":true},"number":{"ctor":true,"float32":{"base":{"exponent":true,"from-binary-string":true,"from-word":true,"normalize":true,"__namespace__":true,"signbit":true,"significand":true,"to-binary-string":true,"to-int32":true,"to-uint32":true,"to-word":true},"__namespace__":true},"float64":{"base":{"exponent":true,"from-binary-string":true,"from-words":true,"get-high-word":true,"get-low-word":true,"normalize":true,"__namespace__":true,"set-high-word":true,"set-low-word":true,"signbit":true,"to-binary-string":true,"to-float32":true,"to-int32":true,"to-uint32":true,"to-words":true},"__namespace__":true},"int32":{"base":{"__namespace__":true,"to-uint32":true},"__namespace__":true},"__namespace__":true,"uint16":{"base":{"from-binary-string":true,"__namespace__":true,"to-binary-string":true},"__namespace__":true},"uint32":{"base":{"from-binary-string":true,"__namespace__":true,"rotl":true,"rotr":true,"to-binary-string":true,"to-int32":true},"__namespace__":true},"uint8":{"base":{"from-binary-string":true,"__namespace__":true,"to-binary-string":true},"__namespace__":true}},"os":{"arch":true,"configdir":true,"homedir":true,"num-cpus":true,"__namespace__":true,"platform":true,"tmpdir":true},"plot":{"base":{"ctor":true},"components":{"svg":{"annotations":true,"axis":true,"background":true,"canvas":true,"clip-path":true,"defs":true,"graph":true,"marks":true,"path":true,"rug":true,"symbols":true,"title":true}},"ctor":true,"__namespace__":true,"sparklines":{"base":{"ctor":true,"__namespace__":true},"__namespace__":true,"unicode":{"column":true,"line":true,"__namespace__":true,"tristate":true,"up-down":true,"win-loss":true}},"unicode":{"stemleaf":true}},"process":{"argv":true,"chdir":true,"cwd":true,"env":true,"getegid":true,"geteuid":true,"getgid":true,"getuid":true,"node-version":true,"__namespace__":true,"read-stdin":true,"umask":true},"proxy":{"ctor":true,"__namespace__":true},"random":{"base":{"arcsine":true,"bernoulli":true,"beta":true,"betaprime":true,"binomial":true,"box-muller":true,"cauchy":true,"chi":true,"chisquare":true,"cosine":true,"discrete-uniform":true,"erlang":true,"exponential":true,"f":true,"frechet":true,"gamma":true,"geometric":true,"gumbel":true,"hypergeometric":true,"improved-ziggurat":true,"invgamma":true,"kumaraswamy":true,"laplace":true,"levy":true,"logistic":true,"lognormal":true,"minstd-shuffle":true,"minstd":true,"mt19937":true,"negative-binomial":true,"normal":true,"__namespace__":true,"pareto-type1":true,"poisson":true,"randi":true,"randn":true,"randu":true,"rayleigh":true,"reviver":true,"t":true,"triangular":true,"uniform":true,"weibull":true},"iter":{"arcsine":true,"bernoulli":true,"beta":true,"betaprime":true,"binomial":true,"box-muller":true,"cauchy":true,"chi":true,"chisquare":true,"cosine":true,"discrete-uniform":true,"erlang":true,"exponential":true,"f":true,"frechet":true,"gamma":true,"geometric":true,"gumbel":true,"hypergeometric":true,"improved-ziggurat":true,"invgamma":true,"kumaraswamy":true,"laplace":true,"levy":true,"logistic":true,"lognormal":true,"minstd-shuffle":true,"minstd":true,"mt19937":true,"negative-binomial":true,"normal":true,"__namespace__":true,"pareto-type1":true,"poisson":true,"randi":true,"randn":true,"randu":true,"rayleigh":true,"t":true,"triangular":true,"uniform":true,"weibull":true},"__namespace__":true,"sample":true,"shuffle":true,"streams":{"arcsine":true,"bernoulli":true,"beta":true,"betaprime":true,"binomial":true,"box-muller":true,"cauchy":true,"chi":true,"chisquare":true,"cosine":true,"discrete-uniform":true,"erlang":true,"exponential":true,"f":true,"frechet":true,"gamma":true,"geometric":true,"gumbel":true,"hypergeometric":true,"improved-ziggurat":true,"invgamma":true,"kumaraswamy":true,"laplace":true,"levy":true,"logistic":true,"lognormal":true,"minstd-shuffle":true,"minstd":true,"mt19937":true,"negative-binomial":true,"normal":true,"__namespace__":true,"pareto-type1":true,"poisson":true,"randi":true,"randn":true,"randu":true,"rayleigh":true,"t":true,"triangular":true,"uniform":true,"weibull":true}},"regexp":{"basename-posix":true,"basename-windows":true,"basename":true,"color-hexadecimal":true,"decimal-number":true,"dirname-posix":true,"dirname-windows":true,"dirname":true,"eol":true,"extended-length-path":true,"extname-posix":true,"extname-windows":true,"extname":true,"filename-posix":true,"filename-windows":true,"filename":true,"function-name":true,"native-function":true,"__namespace__":true,"regexp":true,"unc-path":true,"utf16-surrogate-pair":true,"utf16-unpaired-surrogate":true,"whitespace":true},"repl":{"code-blocks":true,"help":true,"info":true,"__namespace__":true,"presentation":true,"server":true,"signature":true,"typed-signature":true},"simulate":{"iter":{"awgn":true,"awln":true,"awun":true,"bartlett-hann-pulse":true,"bartlett-pulse":true,"cosine-wave":true,"dirac-comb":true,"flat-top-pulse":true,"hann-pulse":true,"lanczos-pulse":true,"__namespace__":true,"periodic-sinc":true,"pulse":true,"sawtooth-wave":true,"sine-wave":true,"square-wave":true,"triangle-wave":true},"__namespace__":true},"stats":{"anova1":true,"bartlett-test":true,"base":{"dists":{"arcsine":{"cdf":true,"ctor":true,"entropy":true,"kurtosis":true,"logcdf":true,"logpdf":true,"mean":true,"median":true,"mode":true,"__namespace__":true,"pdf":true,"quantile":true,"skewness":true,"stdev":true,"variance":true},"bernoulli":{"cdf":true,"ctor":true,"entropy":true,"kurtosis":true,"mean":true,"median":true,"mgf":true,"mode":true,"__namespace__":true,"pmf":true,"quantile":true,"skewness":true,"stdev":true,"variance":true},"beta":{"cdf":true,"ctor":true,"entropy":true,"kurtosis":true,"logcdf":true,"logpdf":true,"mean":true,"median":true,"mgf":true,"mode":true,"__namespace__":true,"pdf":true,"quantile":true,"skewness":true,"stdev":true,"variance":true},"betaprime":{"cdf":true,"ctor":true,"kurtosis":true,"logcdf":true,"logpdf":true,"mean":true,"mode":true,"__namespace__":true,"pdf":true,"quantile":true,"skewness":true,"stdev":true,"variance":true},"binomial":{"cdf":true,"ctor":true,"entropy":true,"kurtosis":true,"logpmf":true,"mean":true,"median":true,"mgf":true,"mode":true,"__namespace__":true,"pmf":true,"quantile":true,"skewness":true,"stdev":true,"variance":true},"cauchy":{"cdf":true,"ctor":true,"entropy":true,"logcdf":true,"logpdf":true,"median":true,"mode":true,"__namespace__":true,"pdf":true,"quantile":true},"chi":{"cdf":true,"ctor":true,"entropy":true,"kurtosis":true,"logpdf":true,"mean":true,"mode":true,"__namespace__":true,"pdf":true,"quantile":true,"skewness":true,"stdev":true,"variance":true},"chisquare":{"cdf":true,"ctor":true,"entropy":true,"kurtosis":true,"logpdf":true,"mean":true,"mgf":true,"mode":true,"__namespace__":true,"pdf":true,"quantile":true,"skewness":true,"stdev":true,"variance":true},"cosine":{"cdf":true,"ctor":true,"kurtosis":true,"logcdf":true,"logpdf":true,"mean":true,"median":true,"mgf":true,"mode":true,"__namespace__":true,"pdf":true,"quantile":true,"skewness":true,"stdev":true,"variance":true},"degenerate":{"cdf":true,"ctor":true,"entropy":true,"logcdf":true,"logpdf":true,"logpmf":true,"mean":true,"median":true,"mgf":true,"mode":true,"__namespace__":true,"pdf":true,"pmf":true,"quantile":true,"stdev":true,"variance":true},"discrete-uniform":{"cdf":true,"ctor":true,"entropy":true,"kurtosis":true,"logcdf":true,"logpmf":true,"mean":true,"median":true,"mgf":true,"__namespace__":true,"pmf":true,"quantile":true,"skewness":true,"stdev":true,"variance":true},"erlang":{"cdf":true,"ctor":true,"entropy":true,"kurtosis":true,"logpdf":true,"mean":true,"mgf":true,"mode":true,"__namespace__":true,"pdf":true,"quantile":true,"skewness":true,"stdev":true,"variance":true},"exponential":{"cdf":true,"ctor":true,"entropy":true,"kurtosis":true,"logcdf":true,"logpdf":true,"mean":true,"median":true,"mgf":true,"mode":true,"__namespace__":true,"pdf":true,"quantile":true,"skewness":true,"stdev":true,"variance":true},"f":{"cdf":true,"ctor":true,"entropy":true,"kurtosis":true,"mean":true,"mode":true,"__namespace__":true,"pdf":true,"quantile":true,"skewness":true,"stdev":true,"variance":true},"frechet":{"cdf":true,"ctor":true,"entropy":true,"kurtosis":true,"logcdf":true,"logpdf":true,"mean":true,"median":true,"mode":true,"__namespace__":true,"pdf":true,"quantile":true,"skewness":true,"stdev":true,"variance":true},"gamma":{"cdf":true,"ctor":true,"entropy":true,"kurtosis":true,"logpdf":true,"mean":true,"mgf":true,"mode":true,"__namespace__":true,"pdf":true,"quantile":true,"skewness":true,"stdev":true,"variance":true},"geometric":{"cdf":true,"ctor":true,"entropy":true,"kurtosis":true,"logcdf":true,"logpmf":true,"mean":true,"median":true,"mgf":true,"mode":true,"__namespace__":true,"pmf":true,"quantile":true,"skewness":true,"stdev":true,"variance":true},"gumbel":{"cdf":true,"ctor":true,"entropy":true,"kurtosis":true,"logcdf":true,"logpdf":true,"mean":true,"median":true,"mgf":true,"mode":true,"__namespace__":true,"pdf":true,"quantile":true,"skewness":true,"stdev":true,"variance":true},"hypergeometric":{"cdf":true,"ctor":true,"kurtosis":true,"logpmf":true,"mean":true,"mode":true,"__namespace__":true,"pmf":true,"quantile":true,"skewness":true,"stdev":true,"variance":true},"invgamma":{"cdf":true,"ctor":true,"entropy":true,"kurtosis":true,"logpdf":true,"mean":true,"mode":true,"__namespace__":true,"pdf":true,"quantile":true,"skewness":true,"stdev":true,"variance":true},"kumaraswamy":{"cdf":true,"ctor":true,"kurtosis":true,"logcdf":true,"logpdf":true,"mean":true,"median":true,"mode":true,"__namespace__":true,"pdf":true,"quantile":true,"skewness":true,"stdev":true,"variance":true},"laplace":{"cdf":true,"ctor":true,"entropy":true,"kurtosis":true,"logcdf":true,"logpdf":true,"mean":true,"median":true,"mgf":true,"mode":true,"__namespace__":true,"pdf":true,"quantile":true,"skewness":true,"stdev":true,"variance":true},"levy":{"cdf":true,"ctor":true,"entropy":true,"logcdf":true,"logpdf":true,"mean":true,"median":true,"mode":true,"__namespace__":true,"pdf":true,"quantile":true,"stdev":true,"variance":true},"logistic":{"cdf":true,"ctor":true,"entropy":true,"kurtosis":true,"logcdf":true,"logpdf":true,"mean":true,"median":true,"mgf":true,"mode":true,"__namespace__":true,"pdf":true,"quantile":true,"skewness":true,"stdev":true,"variance":true},"lognormal":{"cdf":true,"ctor":true,"entropy":true,"kurtosis":true,"logpdf":true,"mean":true,"median":true,"mode":true,"__namespace__":true,"pdf":true,"quantile":true,"skewness":true,"stdev":true,"variance":true},"negative-binomial":{"cdf":true,"ctor":true,"kurtosis":true,"logpmf":true,"mean":true,"mgf":true,"mode":true,"__namespace__":true,"pmf":true,"quantile":true,"skewness":true,"stdev":true,"variance":true},"normal":{"cdf":true,"ctor":true,"entropy":true,"kurtosis":true,"logpdf":true,"mean":true,"median":true,"mgf":true,"mode":true,"__namespace__":true,"pdf":true,"quantile":true,"skewness":true,"stdev":true,"variance":true},"__namespace__":true,"pareto-type1":{"cdf":true,"ctor":true,"entropy":true,"kurtosis":true,"logcdf":true,"logpdf":true,"mean":true,"median":true,"mode":true,"__namespace__":true,"pdf":true,"quantile":true,"skewness":true,"stdev":true,"variance":true},"poisson":{"cdf":true,"ctor":true,"entropy":true,"kurtosis":true,"logpmf":true,"mean":true,"median":true,"mgf":true,"mode":true,"__namespace__":true,"pmf":true,"quantile":true,"skewness":true,"stdev":true,"variance":true},"rayleigh":{"cdf":true,"ctor":true,"entropy":true,"kurtosis":true,"logcdf":true,"logpdf":true,"mean":true,"median":true,"mgf":true,"mode":true,"__namespace__":true,"pdf":true,"quantile":true,"skewness":true,"stdev":true,"variance":true},"t":{"cdf":true,"ctor":true,"entropy":true,"kurtosis":true,"logcdf":true,"logpdf":true,"mean":true,"median":true,"mode":true,"__namespace__":true,"pdf":true,"quantile":true,"skewness":true,"stdev":true,"variance":true},"triangular":{"cdf":true,"ctor":true,"entropy":true,"kurtosis":true,"logcdf":true,"logpdf":true,"mean":true,"median":true,"mgf":true,"mode":true,"__namespace__":true,"pdf":true,"quantile":true,"skewness":true,"stdev":true,"variance":true},"truncated-normal":{"__namespace__":true,"pdf":true},"uniform":{"cdf":true,"ctor":true,"entropy":true,"kurtosis":true,"logcdf":true,"logpdf":true,"mean":true,"median":true,"mgf":true,"__namespace__":true,"pdf":true,"quantile":true,"skewness":true,"stdev":true,"variance":true},"weibull":{"cdf":true,"ctor":true,"entropy":true,"kurtosis":true,"logcdf":true,"logpdf":true,"mean":true,"median":true,"mgf":true,"mode":true,"__namespace__":true,"pdf":true,"quantile":true,"skewness":true,"stdev":true,"variance":true}},"__namespace__":true},"binomial-test":true,"chi2gof":true,"fligner-test":true,"incr":{"apcorr":true,"count":true,"covariance":true,"covmat":true,"cv":true,"ewmean":true,"ewstdev":true,"ewvariance":true,"gmean":true,"grubbs":true,"hmean":true,"kurtosis":true,"maape":true,"mae":true,"mapcorr":true,"mape":true,"max":true,"maxabs":true,"mcovariance":true,"mcv":true,"mda":true,"me":true,"mean":true,"meanabs":true,"meanabs2":true,"meanstdev":true,"meanvar":true,"mgmean":true,"mgrubbs":true,"mhmean":true,"midrange":true,"min":true,"minabs":true,"minmax":true,"minmaxabs":true,"mmaape":true,"mmae":true,"mmape":true,"mmax":true,"mmaxabs":true,"mmda":true,"mme":true,"mmean":true,"mmeanabs":true,"mmeanabs2":true,"mmeanstdev":true,"mmeanvar":true,"mmidrange":true,"mmin":true,"mminabs":true,"mminmax":true,"mminmaxabs":true,"mmpe":true,"mmse":true,"mpcorr":true,"mpcorr2":true,"mpcorrdist":true,"mpe":true,"mprod":true,"mrange":true,"mrmse":true,"mrss":true,"mse":true,"mstdev":true,"msum":true,"msumabs":true,"msumabs2":true,"msummary":true,"msumprod":true,"mvariance":true,"mvmr":true,"__namespace__":true,"pcorr":true,"pcorr2":true,"pcorrdist":true,"pcorrdistmat":true,"pcorrmat":true,"prod":true,"range":true,"rmse":true,"rss":true,"skewness":true,"stdev":true,"sum":true,"sumabs":true,"sumabs2":true,"summary":true,"sumprod":true,"variance":true,"vmr":true,"wmean":true},"iter":{"cugmean":true,"cuhmean":true,"cumax":true,"cumaxabs":true,"cumean":true,"cumeanabs":true,"cumeanabs2":true,"cumidrange":true,"cumin":true,"cuminabs":true,"cuprod":true,"curange":true,"cusum":true,"cusumabs":true,"cusumabs2":true,"max":true,"maxabs":true,"mean":true,"meanabs":true,"meanabs2":true,"midrange":true,"min":true,"minabs":true,"mmax":true,"mmaxabs":true,"mmean":true,"mmeanabs":true,"mmeanabs2":true,"mmidrange":true,"mmin":true,"mminabs":true,"mprod":true,"mrange":true,"msum":true,"msumabs":true,"msumabs2":true,"__namespace__":true,"prod":true,"range":true,"stdev":true,"sum":true,"sumabs":true,"sumabs2":true,"variance":true},"kde2d":true,"kruskal-test":true,"kstest":true,"lowess":true,"__namespace__":true,"pcorrtest":true,"ranks":true,"ttest":true,"ttest2":true,"vartest":true,"ztest":true,"ztest2":true},"streams":{"node":{"debug-sink":true,"debug":true,"empty":true,"from-array":true,"from-circular-array":true,"from-constant":true,"from-iterator":true,"from-strided-array":true,"inspect-sink":true,"inspect":true,"join":true,"__namespace__":true,"split":true,"stderr":true,"stdin":true,"stdout":true,"transform":true},"__namespace__":true},"strided":{"common":true,"math":{"special":{"dabs":true}},"__namespace__":true},"string":{"capitalize":true,"ends-with":true,"from-code-point":true,"left-pad":true,"left-trim":true,"lowercase":true,"__namespace__":true,"pad":true,"percent-encode":true,"remove-first":true,"remove-last":true,"remove-punctuation":true,"remove-utf8-bom":true,"remove-words":true,"repeat":true,"replace":true,"reverse":true,"right-pad":true,"right-trim":true,"startcase":true,"starts-with":true,"trim":true,"uncapitalize":true,"uppercase":true,"utf16-to-utf8-array":true},"symbol":{"async-iterator":true,"ctor":true,"iterator":true,"__namespace__":true},"time":{"day-of-quarter":true,"day-of-year":true,"days-in-month":true,"days-in-year":true,"hours-in-month":true,"hours-in-year":true,"iso-weeks-in-year":true,"minutes-in-month":true,"minutes-in-year":true,"now":true,"__namespace__":true,"quarter-of-year":true,"seconds-in-month":true,"seconds-in-year":true,"tic":true,"toc":true},"tools":{"cli":true,"disposable-http-server":true,"library-manifest":true,"__namespace__":true,"simple-http-server":true},"types":true,"utils":{"any-by-right":true,"any-by":true,"any":true,"append":true,"argument-function":true,"async":{"any-by-right":true,"any-by":true,"bifurcate-by":true,"compose":true,"count-by":true,"do-until":true,"do-while":true,"every-by-right":true,"every-by":true,"for-each-right":true,"for-each":true,"function-sequence":true,"group-by":true,"if-else":true,"if-then":true,"inmap-right":true,"inmap":true,"map-function":true,"map-keys":true,"map-values":true,"none-by-right":true,"none-by":true,"__namespace__":true,"reduce-right":true,"reduce":true,"series-waterfall":true,"some-by-right":true,"some-by":true,"tabulate-by":true,"try-catch":true,"try-then":true,"until":true,"while":true},"bifurcate-by":true,"bifurcate-in":true,"bifurcate-own":true,"bifurcate":true,"capitalize-keys":true,"circular-buffer":true,"compose":true,"constant-function":true,"constructor-name":true,"convert-path":true,"copy":true,"count-by":true,"curry-right":true,"curry":true,"deep-get":true,"deep-pluck":true,"deep-set":true,"define-configurable-read-only-accessor":true,"define-configurable-read-only-property":true,"define-configurable-read-write-accessor":true,"define-configurable-write-only-accessor":true,"define-memoized-configurable-read-only-property":true,"define-memoized-property":true,"define-memoized-read-only-property":true,"define-nonenumerable-property":true,"define-nonenumerable-read-only-accessor":true,"define-nonenumerable-read-only-property":true,"define-nonenumerable-read-write-accessor":true,"define-nonenumerable-write-only-accessor":true,"define-properties":true,"define-property":true,"define-read-only-accessor":true,"define-read-only-property":true,"define-read-write-accessor":true,"define-write-only-accessor":true,"dirname":true,"do-until-each-right":true,"do-until-each":true,"do-until":true,"do-while-each-right":true,"do-while-each":true,"do-while":true,"doubly-linked-list":true,"entries-in":true,"entries":true,"enumerable-properties-in":true,"enumerable-properties":true,"enumerable-property-symbols-in":true,"enumerable-property-symbols":true,"escape-regexp-string":true,"eval":true,"every-by-right":true,"every-by":true,"every":true,"extname":true,"fifo":true,"find":true,"flatten-array":true,"flatten-object":true,"for-each-right":true,"for-each":true,"for-in":true,"for-own":true,"from-entries":true,"function-name":true,"function-sequence":true,"get-prototype-of":true,"global":true,"group-by":true,"group-in":true,"group-own":true,"group":true,"identity-function":true,"if-else":true,"if-then":true,"index-of":true,"inherit":true,"inherited-enumerable-properties":true,"inherited-enumerable-property-symbols":true,"inherited-keys":true,"inherited-nonenumerable-properties":true,"inherited-nonenumerable-property-names":true,"inherited-nonenumerable-property-symbols":true,"inherited-properties":true,"inherited-property-descriptor":true,"inherited-property-descriptors":true,"inherited-property-names":true,"inherited-property-symbols":true,"inherited-writable-properties":true,"inherited-writable-property-names":true,"inherited-writable-property-symbols":true,"inmap-right":true,"inmap":true,"key-by-right":true,"key-by":true,"keys-in":true,"keys":true,"linked-list":true,"lowercase-keys":true,"map-function":true,"map-keys":true,"map-values":true,"memoize":true,"merge":true,"move-property":true,"named-typed-tuple":true,"native-class":true,"none-by-right":true,"none-by":true,"none":true,"nonenumerable-properties-in":true,"nonenumerable-properties":true,"nonenumerable-property-names-in":true,"nonenumerable-property-names":true,"nonenumerable-property-symbols-in":true,"nonenumerable-property-symbols":true,"nonindex-keys":true,"noop":true,"object-inverse-by":true,"object-inverse":true,"omit-by":true,"omit":true,"open-url":true,"__namespace__":true,"papply-right":true,"papply":true,"parallel":true,"parse-json":true,"pick-by":true,"pick":true,"pluck":true,"pop":true,"prepend":true,"properties-in":true,"properties":true,"property-descriptor-in":true,"property-descriptor":true,"property-descriptors-in":true,"property-descriptors":true,"property-names-in":true,"property-names":true,"property-symbols-in":true,"property-symbols":true,"push":true,"real-max":true,"real-min":true,"reduce-right":true,"reduce":true,"regexp-from-string":true,"reorder-arguments":true,"reverse-arguments":true,"safe-int-max":true,"safe-int-min":true,"shift":true,"size-of":true,"some-by-right":true,"some-by":true,"some":true,"stack":true,"tabulate-by":true,"tabulate":true,"timeit":true,"try-catch":true,"try-function":true,"try-require":true,"try-then":true,"type-max":true,"type-min":true,"type-of":true,"uncapitalize-keys":true,"uncurry-right":true,"uncurry":true,"unshift":true,"until-each-right":true,"until-each":true,"until":true,"unzip":true,"uppercase-keys":true,"values-in":true,"values":true,"while-each-right":true,"while-each":true,"while":true,"writable-properties-in":true,"writable-properties":true,"writable-property-names-in":true,"writable-property-names":true,"writable-property-symbols-in":true,"writable-property-symbols":true,"zip":true}}}}}}